lotronexyz12_sdk/__init__.py
lotronexyz12_sdk/endpoints.py
sdk/__init__.py
sdk/endpoints.py
sdk/sdk.py
lotronexyz12_sdk-0.1.3.dist-info/METADATA
lotronexyz12_sdk-0.1.3.dist-info/WHEEL
lotronexyz12_sdk-0.1.3.dist-info/top_level.txt
lotronexyz12_sdk-0.1.3.dist-info/RECORD
