Metadata-Version: 2.1
Name: lotronexyz12-sdk
Version: 0.1.3
Summary: LOTR coding test
Author: Alex
Author-email: 
Requires-Python: >=3.10.9
Requires-Dist: requests
